figvis/__init__.py
figvis/cli/__init__.py
figvis/cli/main.py
figvis/data/__init__.py
figvis/figment/__init__.py
figvis/figment/_constants.py
figvis/figment/_helpers.py
figvis/figment/basic.py
figvis/figment/raster.py
figvis/renderer.py
figvis/svg_to_pdf.py
figvis/templates/base/svg.jinja2
figvis/transform/__init__.py
figvis-0.1.0.dist-info/entry_points.txt
figvis-0.1.0.dist-info/WHEEL
figvis-0.1.0.dist-info/METADATA
figvis-0.1.0.dist-info/RECORD
